npwt/__init__.py
npwt/main.py
npwt-0.0.0.dist-info/LICENSE
npwt-0.0.0.dist-info/METADATA
npwt-0.0.0.dist-info/WHEEL
npwt-0.0.0.dist-info/entry_points.txt
npwt-0.0.0.dist-info/top_level.txt
npwt-0.0.0.dist-info/RECORD
