Metadata-Version: 2.1
Name: npwt
Version: 0.0.0
Summary: It's a surprise project!
Home-page: https://github.com/omid-b/npwt
Author: omid-b
Author-email: omid.bagherpur@gmail.com
License: UNKNOWN
Platform: UNKNOWN
Classifier: Programming Language :: Python :: 3
Classifier: License :: OSI Approved :: GNU Lesser General Public License v3 or later (LGPLv3+)
Classifier: Operating System :: OS Independent
Requires-Python: >=3.6
License-File: LICENSE
Requires-Dist: numpy (>=1.19)
Requires-Dist: pandas (>=1.1)
Requires-Dist: obspy (>=1.2)
